CDTest/__init__.py
CDTest/codes.py
CDTest-0.0.13.dist-info/LICENSE
CDTest-0.0.13.dist-info/METADATA
CDTest-0.0.13.dist-info/WHEEL
CDTest-0.0.13.dist-info/top_level.txt
CDTest-0.0.13.dist-info/RECORD
