Metadata-Version: 2.1
Name: CDTest
Version: 0.0.13
Summary: Streaming video data via networks
Author: Tushar Suthar
Author-email: Tusharsuthar081@gmail.com
Keywords: python,video,stream,video stream,camera stream,sockets
Classifier: Development Status :: 1 - Planning
Classifier: Intended Audience :: Developers
Classifier: Programming Language :: Python :: 3
Classifier: Operating System :: Unix
Classifier: Operating System :: MacOS :: MacOS X
Classifier: Operating System :: Microsoft :: Windows
License-File: LICENSE
